<odoo>
    <record id="view_rcv_line_tree" model="ir.ui.view">
        <field name="name">l10n_cl.rcv.line.tree</field>
        <field name="model">l10n_cl.rcv.line</field>
        <field name="arch" type="xml">
            <tree>
                <field name="rcv_type"/>
                <field name="document_type"/>
                <field name="folio"/>
                <field name="partner_vat"/>
                <field name="net_amount"/>
                <field name="tax_amount"/>
                <field name="total_amount"/>
                <field name="sii_status"/>
            </tree>
        </field>
    </record>
</odoo>